<?xml version="1.0" encoding="utf-8"?>
<Webservice>
  <!--Estados com webservices próprios-->
  <Estado ID="35" Nome="São Paulo" UF="SP">
    <LocalHomologacao>
      <NFeRecepcao>wsdl\homologacao\HSPCteRecepcao.wsdl</NFeRecepcao>
      <NFeRetRecepcao>wsdl\homologacao\HSPCteRetRecepcao.wsdl</NFeRetRecepcao>
      <NFeCancelamento>wsdl\homologacao\HSPCteCancelamento.wsdl</NFeCancelamento>
      <NFeInutilizacao>wsdl\homologacao\HSPCteInutilizacao.wsdl</NFeInutilizacao>
      <NFeConsulta>wsdl\homologacao\HSPCteConsulta.wsdl</NFeConsulta>
      <NFeStatusServico>wsdl\homologacao\HSPCteStatusServico.wsdl</NFeStatusServico>
      <NFeConsultaCadastro>wsdl\homologacao\HSPCadConsultaCadastro.wsdl</NFeConsultaCadastro>
    </LocalHomologacao>
    <LocalProducao>
      <NFeRecepcao>wsdl\producao\PSPCteRecepcao.wsdl</NFeRecepcao>
      <NFeRetRecepcao>wsdl\producao\PSPCteRetRecepcao.wsdl</NFeRetRecepcao>
      <NFeCancelamento>wsdl\producao\PSPCteCancelamento.wsdl</NFeCancelamento>
      <NFeInutilizacao>wsdl\producao\PSPCteInutilizacao.wsdl</NFeInutilizacao>
      <NFeConsulta>wsdl\producao\PSPCteConsulta.wsdl</NFeConsulta>
      <NFeStatusServico>wsdl\producao\PSPCteStatusServico.wsdl</NFeStatusServico>
      <NFeConsultaCadastro>wsdl\producao\PSPCadConsultaCadastro.wsdl</NFeConsultaCadastro>
    </LocalProducao>
  </Estado>
  <Estado ID="41" Nome="Paraná" UF="PR">
    <LocalHomologacao>
      <NFeRecepcao>wsdl\homologacao\HPRCteRecepcao.wsdl</NFeRecepcao>
      <NFeRetRecepcao>wsdl\homologacao\HPRCteRetRecepcao.wsdl</NFeRetRecepcao>
      <NFeCancelamento>wsdl\homologacao\HPRCteCancelamento.wsdl</NFeCancelamento>
      <NFeInutilizacao>wsdl\homologacao\HPRCteInutilizacao.wsdl</NFeInutilizacao>
      <NFeConsulta>wsdl\homologacao\HPRCteConsulta.wsdl</NFeConsulta>
      <NFeStatusServico>wsdl\homologacao\HPRCteStatusServico.wsdl</NFeStatusServico>
      <NFeConsultaCadastro>wsdl\homologacao\HPRCadConsultaCadastro.wsdl</NFeConsultaCadastro>
    </LocalHomologacao>
    <LocalProducao>
      <NFeRecepcao>wsdl\producao\PPRCteRecepcao.wsdl</NFeRecepcao>
      <NFeRetRecepcao>wsdl\producao\PPRCteRetRecepcao.wsdl</NFeRetRecepcao>
      <NFeCancelamento>wsdl\producao\PPRCteCancelamento.wsdl</NFeCancelamento>
      <NFeInutilizacao>wsdl\producao\PPRCteInutilizacao.wsdl</NFeInutilizacao>
      <NFeConsulta>wsdl\producao\PPRCteConsulta.wsdl</NFeConsulta>
      <NFeStatusServico>wsdl\producao\PPRCteStatusServico.wsdl</NFeStatusServico>
      <NFeConsultaCadastro>wsdl\producao\PPRCadConsultaCadastro.wsdl</NFeConsultaCadastro>
    </LocalProducao>
  </Estado>
  <Estado ID="43" Nome="Rio Grande do Sul" UF="RS">
    <LocalHomologacao>
      <NFeRecepcao>wsdl\homologacao\HRSCteRecepcao.wsdl</NFeRecepcao>
      <NFeRetRecepcao>wsdl\homologacao\HRSCteRetRecepcao.wsdl</NFeRetRecepcao>
      <NFeCancelamento>wsdl\homologacao\HRSCteCancelamento.wsdl</NFeCancelamento>
      <NFeInutilizacao>wsdl\homologacao\HRSCteInutilizacao.wsdl</NFeInutilizacao>
      <NFeConsulta>wsdl\homologacao\HRSCteConsulta.wsdl</NFeConsulta>
      <NFeStatusServico>wsdl\homologacao\HRSCteStatusServico.wsdl</NFeStatusServico>
      <NFeConsultaCadastro>wsdl\homologacao\HRSCadConsultaCadastro.wsdl</NFeConsultaCadastro>
    </LocalHomologacao>
    <LocalProducao>
      <NFeRecepcao>wsdl\producao\PRSCteRecepcao.wsdl</NFeRecepcao>
      <NFeRetRecepcao>wsdl\producao\PRSCteRetRecepcao.wsdl</NFeRetRecepcao>
      <NFeCancelamento>wsdl\producao\PRSCteCancelamento.wsdl</NFeCancelamento>
      <NFeInutilizacao>wsdl\producao\PRSCteInutilizacao.wsdl</NFeInutilizacao>
      <NFeConsulta>wsdl\producao\PRSCteConsulta.wsdl</NFeConsulta>
      <NFeStatusServico>wsdl\producao\PRSCteStatusServico.wsdl</NFeStatusServico>
      <NFeConsultaCadastro>wsdl\producao\PRSCadConsultaCadastro.wsdl</NFeConsultaCadastro>
    </LocalProducao>
  </Estado>
  <Estado ID="31" Nome="Minas Gerais" UF="MG">
    <LocalHomologacao>
      <NFeRecepcao>wsdl\homologacao\HMGCteRecepcao.wsdl</NFeRecepcao>
      <NFeRetRecepcao>wsdl\homologacao\HMGCteRetRecepcao.wsdl</NFeRetRecepcao>
      <NFeCancelamento>wsdl\homologacao\HMGCteCancelamento.wsdl</NFeCancelamento>
      <NFeInutilizacao>wsdl\homologacao\HMGCteInutilizacao.wsdl</NFeInutilizacao>
      <NFeConsulta>wsdl\homologacao\HMGCteConsulta.wsdl</NFeConsulta>
      <NFeStatusServico>wsdl\homologacao\HMGCteStatusServico.wsdl</NFeStatusServico>
      <NFeConsultaCadastro>wsdl\homologacao\HMGCadConsultaCadastro.wsdl</NFeConsultaCadastro>
    </LocalHomologacao>
    <LocalProducao>
      <NFeRecepcao>wsdl\producao\PMGCteRecepcao.wsdl</NFeRecepcao>
      <NFeRetRecepcao>wsdl\producao\PMGCteRetRecepcao.wsdl</NFeRetRecepcao>
      <NFeCancelamento>wsdl\producao\PMGCteCancelamento.wsdl</NFeCancelamento>
      <NFeInutilizacao>wsdl\producao\PMGCteInutilizacao.wsdl</NFeInutilizacao>
      <NFeConsulta>wsdl\producao\PMGCteConsulta.wsdl</NFeConsulta>
      <NFeStatusServico>wsdl\producao\PMGCteStatusServico.wsdl</NFeStatusServico>
      <NFeConsultaCadastro>wsdl\producao\PMGCadConsultaCadastro.wsdl</NFeConsultaCadastro>
    </LocalProducao>
  </Estado>
  <Estado ID="50" Nome="Mato Grosso do Sul" UF="MS">
    <LocalHomologacao>
      <NFeRecepcao>wsdl\homologacao\HMSCteRecepcao.wsdl</NFeRecepcao>
      <NFeRetRecepcao>wsdl\homologacao\HMSCteRetRecepcao.wsdl</NFeRetRecepcao>
      <NFeCancelamento>wsdl\homologacao\HMSCteCancelamento.wsdl</NFeCancelamento>
      <NFeInutilizacao>wsdl\homologacao\HMSCteInutilizacao.wsdl</NFeInutilizacao>
      <NFeConsulta>wsdl\homologacao\HMSCteConsulta.wsdl</NFeConsulta>
      <NFeStatusServico>wsdl\homologacao\HMSCteStatusServico.wsdl</NFeStatusServico>
      <NFeConsultaCadastro>wsdl\homologacao\HMSCadConsultaCadastro.wsdl</NFeConsultaCadastro>
    </LocalHomologacao>
    <LocalProducao>
      <NFeRecepcao>wsdl\producao\PMSCteRecepcao.wsdl</NFeRecepcao>
      <NFeRetRecepcao>wsdl\producao\PMSCteRetRecepcao.wsdl</NFeRetRecepcao>
      <NFeCancelamento>wsdl\producao\PMSCteCancelamento.wsdl</NFeCancelamento>
      <NFeInutilizacao>wsdl\producao\PMSCteInutilizacao.wsdl</NFeInutilizacao>
      <NFeConsulta>wsdl\producao\PMSCteConsulta.wsdl</NFeConsulta>
      <NFeStatusServico>wsdl\producao\PMSCteStatusServico.wsdl</NFeStatusServico>
      <NFeConsultaCadastro>wsdl\producao\PMSCadConsultaCadastro.wsdl</NFeConsultaCadastro>
    </LocalProducao>
  </Estado>
  <Estado ID="51" Nome="Mato Grosso" UF="MT">
    <LocalHomologacao>
      <NFeRecepcao>wsdl\homologacao\HMTCteRecepcao.wsdl</NFeRecepcao>
      <NFeRetRecepcao>wsdl\homologacao\HMTCteRetRecepcao.wsdl</NFeRetRecepcao>
      <NFeCancelamento>wsdl\homologacao\HMTCteCancelamento.wsdl</NFeCancelamento>
      <NFeInutilizacao>wsdl\homologacao\HMTCteInutilizacao.wsdl</NFeInutilizacao>
      <NFeConsulta>wsdl\homologacao\HMTCteConsulta.wsdl</NFeConsulta>
      <NFeStatusServico>wsdl\homologacao\HMTCteStatusServico.wsdl</NFeStatusServico>
      <NFeConsultaCadastro>wsdl\homologacao\HMTCadConsultaCadastro.wsdl</NFeConsultaCadastro>
    </LocalHomologacao>
    <LocalProducao>
      <NFeRecepcao>wsdl\producao\PMTCteRecepcao.wsdl</NFeRecepcao>
      <NFeRetRecepcao>wsdl\producao\PMTCteRetRecepcao.wsdl</NFeRetRecepcao>
      <NFeCancelamento>wsdl\producao\PMTCteCancelamento.wsdl</NFeCancelamento>
      <NFeInutilizacao>wsdl\producao\PMTCteInutilizacao.wsdl</NFeInutilizacao>
      <NFeConsulta>wsdl\producao\PMTCteConsulta.wsdl</NFeConsulta>
      <NFeStatusServico>wsdl\producao\PMTCteStatusServico.wsdl</NFeStatusServico>
      <NFeConsultaCadastro>wsdl\producao\PMTCadConsultaCadastro.wsdl</NFeConsultaCadastro>
    </LocalProducao>
  </Estado>
  <!--Estados que utilizam os webservices do Sistema Virtual do Rio Grande do Sul (SVRS)-->
  <Estado ID="15" Nome="Pará" UF="PA">
    <LocalHomologacao>
      <NFeRecepcao>wsdl\homologacao\HSVRSCteRecepcao.wsdl</NFeRecepcao>
      <NFeRetRecepcao>wsdl\homologacao\HSVRSCteRetRecepcao.wsdl</NFeRetRecepcao>
      <NFeCancelamento>wsdl\homologacao\HSVRSCteCancelamento.wsdl</NFeCancelamento>
      <NFeInutilizacao>wsdl\homologacao\HSVRSCteInutilizacao.wsdl</NFeInutilizacao>
      <NFeConsulta>wsdl\homologacao\HSVRSCteConsulta.wsdl</NFeConsulta>
      <NFeStatusServico>wsdl\homologacao\HSVRSCteStatusServico.wsdl</NFeStatusServico>
      <NFeConsultaCadastro>wsdl\homologacao\HSVRSCadConsultaCadastro.wsdl</NFeConsultaCadastro>
    </LocalHomologacao>
    <LocalProducao>
      <NFeRecepcao>wsdl\producao\PSVRSCteRecepcao.wsdl</NFeRecepcao>
      <NFeRetRecepcao>wsdl\producao\PSVRSCteRetRecepcao.wsdl</NFeRetRecepcao>
      <NFeCancelamento>wsdl\producao\PSVRSCteCancelamento.wsdl</NFeCancelamento>
      <NFeInutilizacao>wsdl\producao\PSVRSCteInutilizacao.wsdl</NFeInutilizacao>
      <NFeConsulta>wsdl\producao\PSVRSCteConsulta.wsdl</NFeConsulta>
      <NFeStatusServico>wsdl\producao\PSVRSCteStatusServico.wsdl</NFeStatusServico>
      <NFeConsultaCadastro>wsdl\producao\PSVRSCadConsultaCadastro.wsdl</NFeConsultaCadastro>
    </LocalProducao>
  </Estado>
  <Estado ID="22" Nome="Piaui" UF="PI">
    <LocalHomologacao>
      <NFeRecepcao>wsdl\homologacao\HSVRSCteRecepcao.wsdl</NFeRecepcao>
      <NFeRetRecepcao>wsdl\homologacao\HSVRSCteRetRecepcao.wsdl</NFeRetRecepcao>
      <NFeCancelamento>wsdl\homologacao\HSVRSCteCancelamento.wsdl</NFeCancelamento>
      <NFeInutilizacao>wsdl\homologacao\HSVRSCteInutilizacao.wsdl</NFeInutilizacao>
      <NFeConsulta>wsdl\homologacao\HSVRSCteConsulta.wsdl</NFeConsulta>
      <NFeStatusServico>wsdl\homologacao\HSVRSCteStatusServico.wsdl</NFeStatusServico>
      <NFeConsultaCadastro>wsdl\homologacao\HSVRSCadConsultaCadastro.wsdl</NFeConsultaCadastro>
    </LocalHomologacao>
    <LocalProducao>
      <NFeRecepcao>wsdl\producao\PSVRSCteRecepcao.wsdl</NFeRecepcao>
      <NFeRetRecepcao>wsdl\producao\PSVRSCteRetRecepcao.wsdl</NFeRetRecepcao>
      <NFeCancelamento>wsdl\producao\PSVRSCteCancelamento.wsdl</NFeCancelamento>
      <NFeInutilizacao>wsdl\producao\PSVRSCteInutilizacao.wsdl</NFeInutilizacao>
      <NFeConsulta>wsdl\producao\PSVRSCteConsulta.wsdl</NFeConsulta>
      <NFeStatusServico>wsdl\producao\PSVRSCteStatusServico.wsdl</NFeStatusServico>
      <NFeConsultaCadastro>wsdl\producao\PSVRSCadConsultaCadastro.wsdl</NFeConsultaCadastro>
    </LocalProducao>
  </Estado>
  <Estado ID="32" Nome="Espírito Santo" UF="ES">
    <LocalHomologacao>
      <NFeRecepcao>wsdl\homologacao\HSVRSCteRecepcao.wsdl</NFeRecepcao>
      <NFeRetRecepcao>wsdl\homologacao\HSVRSCteRetRecepcao.wsdl</NFeRetRecepcao>
      <NFeCancelamento>wsdl\homologacao\HSVRSCteCancelamento.wsdl</NFeCancelamento>
      <NFeInutilizacao>wsdl\homologacao\HSVRSCteInutilizacao.wsdl</NFeInutilizacao>
      <NFeConsulta>wsdl\homologacao\HSVRSCteConsulta.wsdl</NFeConsulta>
      <NFeStatusServico>wsdl\homologacao\HSVRSCteStatusServico.wsdl</NFeStatusServico>
      <NFeConsultaCadastro>wsdl\homologacao\HSVRSCadConsultaCadastro.wsdl</NFeConsultaCadastro>
    </LocalHomologacao>
    <LocalProducao>
      <NFeRecepcao>wsdl\producao\PSVRSCteRecepcao.wsdl</NFeRecepcao>
      <NFeRetRecepcao>wsdl\producao\PSVRSCteRetRecepcao.wsdl</NFeRetRecepcao>
      <NFeCancelamento>wsdl\producao\PSVRSCteCancelamento.wsdl</NFeCancelamento>
      <NFeInutilizacao>wsdl\producao\PSVRSCteInutilizacao.wsdl</NFeInutilizacao>
      <NFeConsulta>wsdl\producao\PSVRSCteConsulta.wsdl</NFeConsulta>
      <NFeStatusServico>wsdl\producao\PSVRSCteStatusServico.wsdl</NFeStatusServico>
      <NFeConsultaCadastro>wsdl\producao\PSVRSCadConsultaCadastro.wsdl</NFeConsultaCadastro>
    </LocalProducao>
  </Estado>
  <Estado ID="13" Nome="Amazonas" UF="AM">
    <LocalHomologacao>
      <NFeRecepcao>wsdl\homologacao\HSVRSCteRecepcao.wsdl</NFeRecepcao>
      <NFeRetRecepcao>wsdl\homologacao\HSVRSCteRetRecepcao.wsdl</NFeRetRecepcao>
      <NFeCancelamento>wsdl\homologacao\HSVRSCteCancelamento.wsdl</NFeCancelamento>
      <NFeInutilizacao>wsdl\homologacao\HSVRSCteInutilizacao.wsdl</NFeInutilizacao>
      <NFeConsulta>wsdl\homologacao\HSVRSCteConsulta.wsdl</NFeConsulta>
      <NFeStatusServico>wsdl\homologacao\HSVRSCteStatusServico.wsdl</NFeStatusServico>
      <NFeConsultaCadastro>wsdl\homologacao\HSVRSCadConsultaCadastro.wsdl</NFeConsultaCadastro>
    </LocalHomologacao>
    <LocalProducao>
      <NFeRecepcao>wsdl\producao\PSVRSCteRecepcao.wsdl</NFeRecepcao>
      <NFeRetRecepcao>wsdl\producao\PSVRSCteRetRecepcao.wsdl</NFeRetRecepcao>
      <NFeCancelamento>wsdl\producao\PSVRSCteCancelamento.wsdl</NFeCancelamento>
      <NFeInutilizacao>wsdl\producao\PSVRSCteInutilizacao.wsdl</NFeInutilizacao>
      <NFeConsulta>wsdl\producao\PSVRSCteConsulta.wsdl</NFeConsulta>
      <NFeStatusServico>wsdl\producao\PSVRSCteStatusServico.wsdl</NFeStatusServico>
      <NFeConsultaCadastro>wsdl\producao\PSVRSCadConsultaCadastro.wsdl</NFeConsultaCadastro>
    </LocalProducao>
  </Estado>
  <Estado ID="29" Nome="Bahia" UF="BA">
    <LocalHomologacao>
      <NFeRecepcao>wsdl\homologacao\HSVRSCteRecepcao.wsdl</NFeRecepcao>
      <NFeRetRecepcao>wsdl\homologacao\HSVRSCteRetRecepcao.wsdl</NFeRetRecepcao>
      <NFeCancelamento>wsdl\homologacao\HSVRSCteCancelamento.wsdl</NFeCancelamento>
      <NFeInutilizacao>wsdl\homologacao\HSVRSCteInutilizacao.wsdl</NFeInutilizacao>
      <NFeConsulta>wsdl\homologacao\HSVRSCteConsulta.wsdl</NFeConsulta>
      <NFeStatusServico>wsdl\homologacao\HSVRSCteStatusServico.wsdl</NFeStatusServico>
      <NFeConsultaCadastro>wsdl\homologacao\HSVRSCadConsultaCadastro.wsdl</NFeConsultaCadastro>
    </LocalHomologacao>
    <LocalProducao>
      <NFeRecepcao>wsdl\producao\PSVRSCteRecepcao.wsdl</NFeRecepcao>
      <NFeRetRecepcao>wsdl\producao\PSVRSCteRetRecepcao.wsdl</NFeRetRecepcao>
      <NFeCancelamento>wsdl\producao\PSVRSCteCancelamento.wsdl</NFeCancelamento>
      <NFeInutilizacao>wsdl\producao\PSVRSCteInutilizacao.wsdl</NFeInutilizacao>
      <NFeConsulta>wsdl\producao\PSVRSCteConsulta.wsdl</NFeConsulta>
      <NFeStatusServico>wsdl\producao\PSVRSCteStatusServico.wsdl</NFeStatusServico>
      <NFeConsultaCadastro>wsdl\producao\PSVRSCadConsultaCadastro.wsdl</NFeConsultaCadastro>
    </LocalProducao>
  </Estado>
  <Estado ID="23" Nome="Ceará" UF="CE">
    <LocalHomologacao>
      <NFeRecepcao>wsdl\homologacao\HSVRSCteRecepcao.wsdl</NFeRecepcao>
      <NFeRetRecepcao>wsdl\homologacao\HSVRSCteRetRecepcao.wsdl</NFeRetRecepcao>
      <NFeCancelamento>wsdl\homologacao\HSVRSCteCancelamento.wsdl</NFeCancelamento>
      <NFeInutilizacao>wsdl\homologacao\HSVRSCteInutilizacao.wsdl</NFeInutilizacao>
      <NFeConsulta>wsdl\homologacao\HSVRSCteConsulta.wsdl</NFeConsulta>
      <NFeStatusServico>wsdl\homologacao\HSVRSCteStatusServico.wsdl</NFeStatusServico>
      <NFeConsultaCadastro>wsdl\homologacao\HSVRSCadConsultaCadastro.wsdl</NFeConsultaCadastro>
    </LocalHomologacao>
    <LocalProducao>
      <NFeRecepcao>wsdl\producao\PSVRSCteRecepcao.wsdl</NFeRecepcao>
      <NFeRetRecepcao>wsdl\producao\PSVRSCteRetRecepcao.wsdl</NFeRetRecepcao>
      <NFeCancelamento>wsdl\producao\PSVRSCteCancelamento.wsdl</NFeCancelamento>
      <NFeInutilizacao>wsdl\producao\PSVRSCteInutilizacao.wsdl</NFeInutilizacao>
      <NFeConsulta>wsdl\producao\PSVRSCteConsulta.wsdl</NFeConsulta>
      <NFeStatusServico>wsdl\producao\PSVRSCteStatusServico.wsdl</NFeStatusServico>
      <NFeConsultaCadastro>wsdl\producao\PSVRSCadConsultaCadastro.wsdl</NFeConsultaCadastro>
    </LocalProducao>
  </Estado>
  <Estado ID="53" Nome="Distrito Federal" UF="DF">
    <LocalHomologacao>
      <NFeRecepcao>wsdl\homologacao\HSVRSCteRecepcao.wsdl</NFeRecepcao>
      <NFeRetRecepcao>wsdl\homologacao\HSVRSCteRetRecepcao.wsdl</NFeRetRecepcao>
      <NFeCancelamento>wsdl\homologacao\HSVRSCteCancelamento.wsdl</NFeCancelamento>
      <NFeInutilizacao>wsdl\homologacao\HSVRSCteInutilizacao.wsdl</NFeInutilizacao>
      <NFeConsulta>wsdl\homologacao\HSVRSCteConsulta.wsdl</NFeConsulta>
      <NFeStatusServico>wsdl\homologacao\HSVRSCteStatusServico.wsdl</NFeStatusServico>
      <NFeConsultaCadastro>wsdl\homologacao\HSVRSCadConsultaCadastro.wsdl</NFeConsultaCadastro>
    </LocalHomologacao>
    <LocalProducao>
      <NFeRecepcao>wsdl\producao\PSVRSCteRecepcao.wsdl</NFeRecepcao>
      <NFeRetRecepcao>wsdl\producao\PSVRSCteRetRecepcao.wsdl</NFeRetRecepcao>
      <NFeCancelamento>wsdl\producao\PSVRSCteCancelamento.wsdl</NFeCancelamento>
      <NFeInutilizacao>wsdl\producao\PSVRSCteInutilizacao.wsdl</NFeInutilizacao>
      <NFeConsulta>wsdl\producao\PSVRSCteConsulta.wsdl</NFeConsulta>
      <NFeStatusServico>wsdl\producao\PSVRSCteStatusServico.wsdl</NFeStatusServico>
      <NFeConsultaCadastro>wsdl\producao\PSVRSCadConsultaCadastro.wsdl</NFeConsultaCadastro>
    </LocalProducao>
  </Estado>
  <Estado ID="52" Nome="Goiás" UF="GO">
    <LocalHomologacao>
      <NFeRecepcao>wsdl\homologacao\HSVRSCteRecepcao.wsdl</NFeRecepcao>
      <NFeRetRecepcao>wsdl\homologacao\HSVRSCteRetRecepcao.wsdl</NFeRetRecepcao>
      <NFeCancelamento>wsdl\homologacao\HSVRSCteCancelamento.wsdl</NFeCancelamento>
      <NFeInutilizacao>wsdl\homologacao\HSVRSCteInutilizacao.wsdl</NFeInutilizacao>
      <NFeConsulta>wsdl\homologacao\HSVRSCteConsulta.wsdl</NFeConsulta>
      <NFeStatusServico>wsdl\homologacao\HSVRSCteStatusServico.wsdl</NFeStatusServico>
      <NFeConsultaCadastro>wsdl\homologacao\HSVRSCadConsultaCadastro.wsdl</NFeConsultaCadastro>
    </LocalHomologacao>
    <LocalProducao>
      <NFeRecepcao>wsdl\producao\PSVRSCteRecepcao.wsdl</NFeRecepcao>
      <NFeRetRecepcao>wsdl\producao\PSVRSCteRetRecepcao.wsdl</NFeRetRecepcao>
      <NFeCancelamento>wsdl\producao\PSVRSCteCancelamento.wsdl</NFeCancelamento>
      <NFeInutilizacao>wsdl\producao\PSVRSCteInutilizacao.wsdl</NFeInutilizacao>
      <NFeConsulta>wsdl\producao\PSVRSCteConsulta.wsdl</NFeConsulta>
      <NFeStatusServico>wsdl\producao\PSVRSCteStatusServico.wsdl</NFeStatusServico>
      <NFeConsultaCadastro>wsdl\producao\PSVRSCadConsultaCadastro.wsdl</NFeConsultaCadastro>
    </LocalProducao>
  </Estado>
  <Estado ID="21" Nome="Maranhão" UF="MA">
    <LocalHomologacao>
      <NFeRecepcao>wsdl\homologacao\HSVRSCteRecepcao.wsdl</NFeRecepcao>
      <NFeRetRecepcao>wsdl\homologacao\HSVRSCteRetRecepcao.wsdl</NFeRetRecepcao>
      <NFeCancelamento>wsdl\homologacao\HSVRSCteCancelamento.wsdl</NFeCancelamento>
      <NFeInutilizacao>wsdl\homologacao\HSVRSCteInutilizacao.wsdl</NFeInutilizacao>
      <NFeConsulta>wsdl\homologacao\HSVRSCteConsulta.wsdl</NFeConsulta>
      <NFeStatusServico>wsdl\homologacao\HSVRSCteStatusServico.wsdl</NFeStatusServico>
      <NFeConsultaCadastro>wsdl\homologacao\HSVRSCadConsultaCadastro.wsdl</NFeConsultaCadastro>
    </LocalHomologacao>
    <LocalProducao>
      <NFeRecepcao>wsdl\producao\PSVRSCteRecepcao.wsdl</NFeRecepcao>
      <NFeRetRecepcao>wsdl\producao\PSVRSCteRetRecepcao.wsdl</NFeRetRecepcao>
      <NFeCancelamento>wsdl\producao\PSVRSCteCancelamento.wsdl</NFeCancelamento>
      <NFeInutilizacao>wsdl\producao\PSVRSCteInutilizacao.wsdl</NFeInutilizacao>
      <NFeConsulta>wsdl\producao\PSVRSCteConsulta.wsdl</NFeConsulta>
      <NFeStatusServico>wsdl\producao\PSVRSCteStatusServico.wsdl</NFeStatusServico>
      <NFeConsultaCadastro>wsdl\producao\PSVRSCadConsultaCadastro.wsdl</NFeConsultaCadastro>
    </LocalProducao>
  </Estado>
  <Estado ID="33" Nome="Rio de Janeiro" UF="RJ">
    <LocalHomologacao>
      <NFeRecepcao>wsdl\homologacao\HSVRSCteRecepcao.wsdl</NFeRecepcao>
      <NFeRetRecepcao>wsdl\homologacao\HSVRSCteRetRecepcao.wsdl</NFeRetRecepcao>
      <NFeCancelamento>wsdl\homologacao\HSVRSCteCancelamento.wsdl</NFeCancelamento>
      <NFeInutilizacao>wsdl\homologacao\HSVRSCteInutilizacao.wsdl</NFeInutilizacao>
      <NFeConsulta>wsdl\homologacao\HSVRSCteConsulta.wsdl</NFeConsulta>
      <NFeStatusServico>wsdl\homologacao\HSVRSCteStatusServico.wsdl</NFeStatusServico>
      <NFeConsultaCadastro>wsdl\homologacao\HSVRSCadConsultaCadastro.wsdl</NFeConsultaCadastro>
    </LocalHomologacao>
    <LocalProducao>
      <NFeRecepcao>wsdl\producao\PSVRSCteRecepcao.wsdl</NFeRecepcao>
      <NFeRetRecepcao>wsdl\producao\PSVRSCteRetRecepcao.wsdl</NFeRetRecepcao>
      <NFeCancelamento>wsdl\producao\PSVRSCteCancelamento.wsdl</NFeCancelamento>
      <NFeInutilizacao>wsdl\producao\PSVRSCteInutilizacao.wsdl</NFeInutilizacao>
      <NFeConsulta>wsdl\producao\PSVRSCteConsulta.wsdl</NFeConsulta>
      <NFeStatusServico>wsdl\producao\PSVRSCteStatusServico.wsdl</NFeStatusServico>
      <NFeConsultaCadastro>wsdl\producao\PSVRSCadConsultaCadastro.wsdl</NFeConsultaCadastro>
    </LocalProducao>
  </Estado>
  <Estado ID="24" Nome="Rio Grande do Norte" UF="RN">
    <LocalHomologacao>
      <NFeRecepcao>wsdl\homologacao\HSVRSCteRecepcao.wsdl</NFeRecepcao>
      <NFeRetRecepcao>wsdl\homologacao\HSVRSCteRetRecepcao.wsdl</NFeRetRecepcao>
      <NFeCancelamento>wsdl\homologacao\HSVRSCteCancelamento.wsdl</NFeCancelamento>
      <NFeInutilizacao>wsdl\homologacao\HSVRSCteInutilizacao.wsdl</NFeInutilizacao>
      <NFeConsulta>wsdl\homologacao\HSVRSCteConsulta.wsdl</NFeConsulta>
      <NFeStatusServico>wsdl\homologacao\HSVRSCteStatusServico.wsdl</NFeStatusServico>
      <NFeConsultaCadastro>wsdl\homologacao\HSVRSCadConsultaCadastro.wsdl</NFeConsultaCadastro>
    </LocalHomologacao>
    <LocalProducao>
      <NFeRecepcao>wsdl\producao\PSVRSCteRecepcao.wsdl</NFeRecepcao>
      <NFeRetRecepcao>wsdl\producao\PSVRSCteRetRecepcao.wsdl</NFeRetRecepcao>
      <NFeCancelamento>wsdl\producao\PSVRSCteCancelamento.wsdl</NFeCancelamento>
      <NFeInutilizacao>wsdl\producao\PSVRSCteInutilizacao.wsdl</NFeInutilizacao>
      <NFeConsulta>wsdl\producao\PSVRSCteConsulta.wsdl</NFeConsulta>
      <NFeStatusServico>wsdl\producao\PSVRSCteStatusServico.wsdl</NFeStatusServico>
      <NFeConsultaCadastro>wsdl\producao\PSVRSCadConsultaCadastro.wsdl</NFeConsultaCadastro>
    </LocalProducao>
  </Estado>
  <Estado ID="11" Nome="Rondonia" UF="RO">
    <LocalHomologacao>
      <NFeRecepcao>wsdl\homologacao\HSVRSCteRecepcao.wsdl</NFeRecepcao>
      <NFeRetRecepcao>wsdl\homologacao\HSVRSCteRetRecepcao.wsdl</NFeRetRecepcao>
      <NFeCancelamento>wsdl\homologacao\HSVRSCteCancelamento.wsdl</NFeCancelamento>
      <NFeInutilizacao>wsdl\homologacao\HSVRSCteInutilizacao.wsdl</NFeInutilizacao>
      <NFeConsulta>wsdl\homologacao\HSVRSCteConsulta.wsdl</NFeConsulta>
      <NFeStatusServico>wsdl\homologacao\HSVRSCteStatusServico.wsdl</NFeStatusServico>
      <NFeConsultaCadastro>wsdl\homologacao\HSVRSCadConsultaCadastro.wsdl</NFeConsultaCadastro>
    </LocalHomologacao>
    <LocalProducao>
      <NFeRecepcao>wsdl\producao\PSVRSCteRecepcao.wsdl</NFeRecepcao>
      <NFeRetRecepcao>wsdl\producao\PSVRSCteRetRecepcao.wsdl</NFeRetRecepcao>
      <NFeCancelamento>wsdl\producao\PSVRSCteCancelamento.wsdl</NFeCancelamento>
      <NFeInutilizacao>wsdl\producao\PSVRSCteInutilizacao.wsdl</NFeInutilizacao>
      <NFeConsulta>wsdl\producao\PSVRSCteConsulta.wsdl</NFeConsulta>
      <NFeStatusServico>wsdl\producao\PSVRSCteStatusServico.wsdl</NFeStatusServico>
      <NFeConsultaCadastro>wsdl\producao\PSVRSCadConsultaCadastro.wsdl</NFeConsultaCadastro>
    </LocalProducao>
  </Estado>
  <Estado ID="42" Nome="Santa Catarina" UF="SC">
    <LocalHomologacao>
      <NFeRecepcao>wsdl\homologacao\HSVRSCteRecepcao.wsdl</NFeRecepcao>
      <NFeRetRecepcao>wsdl\homologacao\HSVRSCteRetRecepcao.wsdl</NFeRetRecepcao>
      <NFeCancelamento>wsdl\homologacao\HSVRSCteCancelamento.wsdl</NFeCancelamento>
      <NFeInutilizacao>wsdl\homologacao\HSVRSCteInutilizacao.wsdl</NFeInutilizacao>
      <NFeConsulta>wsdl\homologacao\HSVRSCteConsulta.wsdl</NFeConsulta>
      <NFeStatusServico>wsdl\homologacao\HSVRSCteStatusServico.wsdl</NFeStatusServico>
      <NFeConsultaCadastro>wsdl\homologacao\HSVRSCadConsultaCadastro.wsdl</NFeConsultaCadastro>
    </LocalHomologacao>
    <LocalProducao>
      <NFeRecepcao>wsdl\producao\PSVRSCteRecepcao.wsdl</NFeRecepcao>
      <NFeRetRecepcao>wsdl\producao\PSVRSCteRetRecepcao.wsdl</NFeRetRecepcao>
      <NFeCancelamento>wsdl\producao\PSVRSCteCancelamento.wsdl</NFeCancelamento>
      <NFeInutilizacao>wsdl\producao\PSVRSCteInutilizacao.wsdl</NFeInutilizacao>
      <NFeConsulta>wsdl\producao\PSVRSCteConsulta.wsdl</NFeConsulta>
      <NFeStatusServico>wsdl\producao\PSVRSCteStatusServico.wsdl</NFeStatusServico>
      <NFeConsultaCadastro>wsdl\producao\PSVRSCadConsultaCadastro.wsdl</NFeConsultaCadastro>
    </LocalProducao>
  </Estado>
  <Estado ID="28" Nome="Sergipe" UF="SE">
    <LocalHomologacao>
      <NFeRecepcao>wsdl\homologacao\HSVRSCteRecepcao.wsdl</NFeRecepcao>
      <NFeRetRecepcao>wsdl\homologacao\HSVRSCteRetRecepcao.wsdl</NFeRetRecepcao>
      <NFeCancelamento>wsdl\homologacao\HSVRSCteCancelamento.wsdl</NFeCancelamento>
      <NFeInutilizacao>wsdl\homologacao\HSVRSCteInutilizacao.wsdl</NFeInutilizacao>
      <NFeConsulta>wsdl\homologacao\HSVRSCteConsulta.wsdl</NFeConsulta>
      <NFeStatusServico>wsdl\homologacao\HSVRSCteStatusServico.wsdl</NFeStatusServico>
      <NFeConsultaCadastro>wsdl\homologacao\HSVRSCadConsultaCadastro.wsdl</NFeConsultaCadastro>
    </LocalHomologacao>
    <LocalProducao>
      <NFeRecepcao>wsdl\producao\PSVRSCteRecepcao.wsdl</NFeRecepcao>
      <NFeRetRecepcao>wsdl\producao\PSVRSCteRetRecepcao.wsdl</NFeRetRecepcao>
      <NFeCancelamento>wsdl\producao\PSVRSCteCancelamento.wsdl</NFeCancelamento>
      <NFeInutilizacao>wsdl\producao\PSVRSCteInutilizacao.wsdl</NFeInutilizacao>
      <NFeConsulta>wsdl\producao\PSVRSCteConsulta.wsdl</NFeConsulta>
      <NFeStatusServico>wsdl\producao\PSVRSCteStatusServico.wsdl</NFeStatusServico>
      <NFeConsultaCadastro>wsdl\producao\PSVRSCadConsultaCadastro.wsdl</NFeConsultaCadastro>
    </LocalProducao>
  </Estado>
  <Estado ID="17" Nome="Tocantins" UF="TO">
    <LocalHomologacao>
      <NFeRecepcao>wsdl\homologacao\HSVRSCteRecepcao.wsdl</NFeRecepcao>
      <NFeRetRecepcao>wsdl\homologacao\HSVRSCteRetRecepcao.wsdl</NFeRetRecepcao>
      <NFeCancelamento>wsdl\homologacao\HSVRSCteCancelamento.wsdl</NFeCancelamento>
      <NFeInutilizacao>wsdl\homologacao\HSVRSCteInutilizacao.wsdl</NFeInutilizacao>
      <NFeConsulta>wsdl\homologacao\HSVRSCteConsulta.wsdl</NFeConsulta>
      <NFeStatusServico>wsdl\homologacao\HSVRSCteStatusServico.wsdl</NFeStatusServico>
      <NFeConsultaCadastro>wsdl\homologacao\HSVRSCadConsultaCadastro.wsdl</NFeConsultaCadastro>
    </LocalHomologacao>
    <LocalProducao>
      <NFeRecepcao>wsdl\producao\PSVRSCteRecepcao.wsdl</NFeRecepcao>
      <NFeRetRecepcao>wsdl\producao\PSVRSCteRetRecepcao.wsdl</NFeRetRecepcao>
      <NFeCancelamento>wsdl\producao\PSVRSCteCancelamento.wsdl</NFeCancelamento>
      <NFeInutilizacao>wsdl\producao\PSVRSCteInutilizacao.wsdl</NFeInutilizacao>
      <NFeConsulta>wsdl\producao\PSVRSCteConsulta.wsdl</NFeConsulta>
      <NFeStatusServico>wsdl\producao\PSVRSCteStatusServico.wsdl</NFeStatusServico>
      <NFeConsultaCadastro>wsdl\producao\PSVRSCadConsultaCadastro.wsdl</NFeConsultaCadastro>
    </LocalProducao>
  </Estado>
  <Estado ID="25" Nome="Paraiba" UF="PB">
    <LocalHomologacao>
      <NFeRecepcao>wsdl\homologacao\HSVRSCteRecepcao.wsdl</NFeRecepcao>
      <NFeRetRecepcao>wsdl\homologacao\HSVRSCteRetRecepcao.wsdl</NFeRetRecepcao>
      <NFeCancelamento>wsdl\homologacao\HSVRSCteCancelamento.wsdl</NFeCancelamento>
      <NFeInutilizacao>wsdl\homologacao\HSVRSCteInutilizacao.wsdl</NFeInutilizacao>
      <NFeConsulta>wsdl\homologacao\HSVRSCteConsulta.wsdl</NFeConsulta>
      <NFeStatusServico>wsdl\homologacao\HSVRSCteStatusServico.wsdl</NFeStatusServico>
      <NFeConsultaCadastro>wsdl\homologacao\HSVRSCadConsultaCadastro.wsdl</NFeConsultaCadastro>
    </LocalHomologacao>
    <LocalProducao>
      <NFeRecepcao>wsdl\producao\PSVRSCteRecepcao.wsdl</NFeRecepcao>
      <NFeRetRecepcao>wsdl\producao\PSVRSCteRetRecepcao.wsdl</NFeRetRecepcao>
      <NFeCancelamento>wsdl\producao\PSVRSCteCancelamento.wsdl</NFeCancelamento>
      <NFeInutilizacao>wsdl\producao\PSVRSCteInutilizacao.wsdl</NFeInutilizacao>
      <NFeConsulta>wsdl\producao\PSVRSCteConsulta.wsdl</NFeConsulta>
      <NFeStatusServico>wsdl\producao\PSVRSCteStatusServico.wsdl</NFeStatusServico>
      <NFeConsultaCadastro>wsdl\producao\PSVRSCadConsultaCadastro.wsdl</NFeConsultaCadastro>
    </LocalProducao>
  </Estado>
  <!-- Estados que utilizam o ambiente de São Paulo -->
  <Estado ID="26" Nome="Pernambuco" UF="PE">
    <LocalHomologacao>
      <NFeRecepcao>wsdl\homologacao\HSPCteRecepcao.wsdl</NFeRecepcao>
      <NFeRetRecepcao>wsdl\homologacao\HSPCteRetRecepcao.wsdl</NFeRetRecepcao>
      <NFeCancelamento>wsdl\homologacao\HSPCteCancelamento.wsdl</NFeCancelamento>
      <NFeInutilizacao>wsdl\homologacao\HSPCteInutilizacao.wsdl</NFeInutilizacao>
      <NFeConsulta>wsdl\homologacao\HSPCteConsulta.wsdl</NFeConsulta>
      <NFeStatusServico>wsdl\homologacao\HSPCteStatusServico.wsdl</NFeStatusServico>
      <NFeConsultaCadastro>wsdl\homologacao\HSPCadConsultaCadastro.wsdl</NFeConsultaCadastro>
    </LocalHomologacao>
    <LocalProducao>
      <NFeRecepcao>wsdl\producao\PSPCteRecepcao.wsdl</NFeRecepcao>
      <NFeRetRecepcao>wsdl\producao\PSPCteRetRecepcao.wsdl</NFeRetRecepcao>
      <NFeCancelamento>wsdl\producao\PSPCteCancelamento.wsdl</NFeCancelamento>
      <NFeInutilizacao>wsdl\producao\PSPCteInutilizacao.wsdl</NFeInutilizacao>
      <NFeConsulta>wsdl\producao\PSPCteConsulta.wsdl</NFeConsulta>
      <NFeStatusServico>wsdl\producao\PSPCteStatusServico.wsdl</NFeStatusServico>
      <NFeConsultaCadastro>wsdl\producao\PSPCadConsultaCadastro.wsdl</NFeConsultaCadastro>
    </LocalProducao>
  </Estado>
  <!--SCAN - Sistema de contingência do ambiente nacional-->
  <Estado ID="902" Nome="Servico de Contingencia Virtual do Rio Grande do Sul" UF="SCVRS">
    <LocalHomologacao>
      <NFeRecepcao>wsdl\homologacao\HSCVRSCteRecepcao.wsdl</NFeRecepcao>
      <NFeRetRecepcao>wsdl\homologacao\HSCVRSCteRetRecepcao.wsdl</NFeRetRecepcao>
      <NFeCancelamento>wsdl\homologacao\HSCVRSCteCancelamento.wsdl</NFeCancelamento>
      <NFeInutilizacao></NFeInutilizacao>
      <NFeConsulta>wsdl\homologacao\HSCVRSCteConsulta.wsdl</NFeConsulta>
      <NFeStatusServico>wsdl\homologacao\HSCVRSCteStatusServico.wsdl</NFeStatusServico>
      <NFeConsultaCadastro></NFeConsultaCadastro>
    </LocalHomologacao>
    <LocalProducao>
      <NFeRecepcao>wsdl\producao\PSCVRSCteRecepcao.wsdl</NFeRecepcao>
      <NFeRetRecepcao>wsdl\producao\PSCVRSCteRetRecepcao.wsdl</NFeRetRecepcao>
      <NFeCancelamento>wsdl\producao\PSCVRSCteCancelamento.wsdl</NFeCancelamento>
      <NFeInutilizacao></NFeInutilizacao>
      <NFeConsulta>wsdl\producao\PSCVRSCteConsulta.wsdl</NFeConsulta>
      <NFeStatusServico>wsdl\producao\PSCVRSCteStatusServico.wsdl</NFeStatusServico>
      <NFeConsultaCadastro></NFeConsultaCadastro>
    </LocalProducao>
  </Estado>
  <Estado ID="903" Nome="Servico de Contingencia Virtual de São Paulo" UF="SCVSP">
    <LocalHomologacao>
      <NFeRecepcao>wsdl\homologacao\HSCVSPCteRecepcao.wsdl</NFeRecepcao>
      <NFeRetRecepcao>wsdl\homologacao\HSCVSPCteRetRecepcao.wsdl</NFeRetRecepcao>
      <NFeCancelamento>wsdl\homologacao\HSCVSPCteCancelamento.wsdl</NFeCancelamento>
      <NFeInutilizacao></NFeInutilizacao>
      <NFeConsulta>wsdl\homologacao\HSCVSPCteConsulta.wsdl</NFeConsulta>
      <NFeStatusServico>wsdl\homologacao\HSCVSPCteStatusServico.wsdl</NFeStatusServico>
      <NFeConsultaCadastro></NFeConsultaCadastro>
    </LocalHomologacao>
    <LocalProducao>
      <NFeRecepcao>wsdl\producao\PSCVSPCteRecepcao.wsdl</NFeRecepcao>
      <NFeRetRecepcao>wsdl\producao\PSCVSPCteRetRecepcao.wsdl</NFeRetRecepcao>
      <NFeCancelamento>wsdl\producao\PSCVSPCteCancelamento.wsdl</NFeCancelamento>
      <NFeInutilizacao></NFeInutilizacao>
      <NFeConsulta>wsdl\producao\PSCVSPCteConsulta.wsdl</NFeConsulta>
      <NFeStatusServico>wsdl\producao\PSCVSPCteStatusServico.wsdl</NFeStatusServico>
      <NFeConsultaCadastro></NFeConsultaCadastro>
    </LocalProducao>
  </Estado>
  <!-- Sequencia de tag´s de template-->
  <Estado ID="999" Nome="Template" UF="XX">
    <LocalHomologacao>
      <NFeRecepcao></NFeRecepcao>
      <NFeRetRecepcao></NFeRetRecepcao>
      <NFeCancelamento></NFeCancelamento>
      <NFeInutilizacao></NFeInutilizacao>
      <NFeConsulta></NFeConsulta>
      <NFeStatusServico></NFeStatusServico>
      <NFeConsultaCadastro></NFeConsultaCadastro>
    </LocalHomologacao>
    <LocalProducao>
      <NFeRecepcao></NFeRecepcao>
      <NFeRetRecepcao></NFeRetRecepcao>
      <NFeCancelamento></NFeCancelamento>
      <NFeInutilizacao></NFeInutilizacao>
      <NFeConsulta></NFeConsulta>
      <NFeStatusServico></NFeStatusServico>
      <NFeConsultaCadastro></NFeConsultaCadastro>
    </LocalProducao>
  </Estado>
</Webservice>